ChristisMongo/__init__.py
ChristisMongo/core/__init__.py
ChristisMongo/core/collection.py
ChristisMongo/core/config_parser.py
ChristisMongo/core/connection.py
ChristisMongo/core/db.py
ChristisMongo/table/__init__.py
ChristisMongo/table/add.py
ChristisMongo/table/delete.py
ChristisMongo/table/get.py
ChristisMongo/table/move.py
ChristisMongo/table/query.py
ChristisMongo-0.21.dist-info/METADATA
ChristisMongo-0.21.dist-info/WHEEL
ChristisMongo-0.21.dist-info/top_level.txt
ChristisMongo-0.21.dist-info/RECORD
